atomtoolkit/IO.py
atomtoolkit/__init__.py
atomtoolkit/atom.py
atomtoolkit/atom_helpers.py
atomtoolkit/transition_strengths.py
atomtoolkit/wigner.py
atomtoolkit/render/__init__.py
atomtoolkit/render/grotrian.py
atomtoolkit/render/lineshapes.py
atomtoolkit/render/spectra.py
Atom_Toolkit-0.1.1.dev5.dist-info/LICENSE
Atom_Toolkit-0.1.1.dev5.dist-info/METADATA
Atom_Toolkit-0.1.1.dev5.dist-info/WHEEL
Atom_Toolkit-0.1.1.dev5.dist-info/top_level.txt
Atom_Toolkit-0.1.1.dev5.dist-info/RECORD
